{
    "attrib_01": "des_attrib_01",
    "attrib_02": "des_attrib_02",
    "attrib_03": "des_attrib_03",
    "attrib_04": "des_attrib_04",
    "attrib_05": "des_attrib_05",
    "attrib_06": "des_attrib_06",
    "attrib_07": "des_attrib_07",
    "attrib_08": "des_attrib_08",
    "attrib_09": "des_attrib_09",
    "attrib_10": "des_attrib_10",
    "attrib_11": "des_attrib_11",
    "attrib_12": "des_attrib_12",
    "attrib_13": "des_attrib_13",
    "attrib_14": "des_attrib_14",
    "attrib_15": "des_attrib_15",
    "attrib_16": "des_attrib_16",
    "attrib_17": "des_attrib_17",
    "attrib_18": "des_attrib_18",
    "attrib_19": "des_attrib_19",
    "attrib_20": "des_attrib_20",
    "attrib_21": "des_attrib_21",
    "attrib_22": "des_attrib_22",
    "attrib_23": "des_attrib_23",
    "attrib_24": "des_attrib_24",
    "attrib_25": "des_attrib_25",
    "attrib_26": "des_attrib_26",
    "attrib_27": "des_attrib_27",
    "attrib_28": "des_attrib_28",
    "attrib_29": "des_attrib_29",
    "attrib_30": "des_attrib_30",
    "attrib_31": "des_attrib_31",
    "attrib_32": "des_attrib_32",
    "attrib_33": "des_attrib_33",
    "attrib_34": "des_attrib_34",
    "attrib_35": "des_attrib_35",
    "attrib_36": "des_attrib_36",
    "attrib_37": "des_attrib_37",
    "attrib_38": "des_attrib_38",
    "attrib_39": "des_attrib_39",
    "attrib_40": "des_attrib_40",
    "attrib_41": "des_attrib_41",
    "attrib_42": "des_attrib_42",
    "attrib_43": "des_attrib_43",
    "attrib_44": "des_attrib_44",
    "attrib_45": "des_attrib_45",
    "attrib_46": "des_attrib_46",
    "attrib_47": "des_attrib_47",
    "conflict_id": "ide_conflict",
    "created": "dat_creation",
    "created_by": "ide_created_by",
    "db_last_upd": "dat_db_last_update",
    "db_last_upd_src": "des_db_last_update_source",
    "last_upd": "dat_last_update",
    "last_upd_by": "ide_last_update_by",
    "modification_num": "num_modification",
    "par_row_id": "ide_par_row",
    "row_id": "ide_row",
    "x_attrib_01": "des_x_attrib_01",
    "x_attrib_02": "des_x_attrib_02",
    "x_attrib_03": "des_x_attrib_03"
}